Bybit_parser/__init__.py
Bybit_parser/core.py
Bybit_parser-0.0.3.dist-info/METADATA
Bybit_parser-0.0.3.dist-info/WHEEL
Bybit_parser-0.0.3.dist-info/top_level.txt
Bybit_parser-0.0.3.dist-info/RECORD
