Metadata-Version: 2.1
Name: Bybit_parser
Version: 0.0.3
Summary: Данная библиотека предназначена для более удобной работы с api bybit
Home-page: https://github.com/boyfws
Author: db.boy
Author-email: minkin.d.d@gmail.com
Keywords: files speedfiles
Classifier: Programming Language :: Python :: 3.11
Classifier: License :: OSI Approved :: MIT License
Classifier: Operating System :: OS Independent
Requires-Python: >=3.5
Requires-Dist: requests
Requires-Dist: pandas
Requires-Dist: numpy
Requires-Dist: tzlocal
